ediacara/Assembly.py
ediacara/Comparator.py
ediacara/__init__.py
ediacara/reports.py
ediacara/version.py
ediacara/report_assets/assembly_report.pug
ediacara/report_assets/report_style.css
ediacara/report_assets/run_simulation_report.pug
ediacara/report_assets/imgs/logo.png
ediacara-0.2.2.dist-info/LICENSE
ediacara-0.2.2.dist-info/METADATA
ediacara-0.2.2.dist-info/WHEEL
ediacara-0.2.2.dist-info/top_level.txt
ediacara-0.2.2.dist-info/RECORD
