Metadata-Version: 2.1
Name: ediacara
Version: 0.2.2
Summary: EGF's alignment reporter
Author: Peter Vegh
License: GPLv3+
Keywords: biology,sequencing
Platform: UNKNOWN
License-File: LICENSE
Requires-Dist: matplotlib
Requires-Dist: numpy
Requires-Dist: pandas
Requires-Dist: weighted-levenshtein
Requires-Dist: biopython
Requires-Dist: dna-features-viewer
Requires-Dist: geneblocks
Requires-Dist: cyvcf2
Requires-Dist: pdf-reports
Requires-Dist: portion
